lcapi/__init__.py
lcapi/__main__.py
lcapi/cli.py
lcapi/commands.py
lcapi/config.py
lcapi-0.9.7.dist-info/LICENSE
lcapi-0.9.7.dist-info/METADATA
lcapi-0.9.7.dist-info/WHEEL
lcapi-0.9.7.dist-info/entry_points.txt
lcapi-0.9.7.dist-info/top_level.txt
lcapi-0.9.7.dist-info/RECORD
